{"puzzle":{"startId":"Q5879","endId":"Q80504","bubbles":[{"id":"Q5879","label":"Johann Wolfgang von Goethe","position":{"x":195,"y":80}},{"id":"Q214622","label":"Nikos Kazantzakis","position":{"x":73.52883991067064,"y":160.91121142537708}},{"id":"Q1394","label":"Vladimir Lenin","position":{"x":196.38294450185703,"y":173.56896452332865}},{"id":"Q855","label":"Joseph Stalin","position":{"x":311.0246239695714,"y":170.5052742992271}},{"id":"Q517","label":"Napoleon","position":{"x":69.18092488248395,"y":273.8357854161178}},{"id":"Q484141","label":"Muhammad Iqbal","position":{"x":204.2926155257509,"y":270.5809110451339}},{"id":"Q12875223","label":"Yannis K. Kordatos","position":{"x":314.7823477971351,"y":270.23095243312105}},{"id":"Q187550","label":"Toyotomi Hideyoshi","position":{"x":68.83222534143282,"y":379.70836475250053}},{"id":"Q2658023","label":"Ioannis Makriyannis","position":{"x":196.90912087588362,"y":375.8134119050648}},{"id":"Q34060","label":"Yizhak Rabin","position":{"x":321.475220926969,"y":376.9158571963839}},{"id":"Q132899","label":"Vyacheslav Molotov","position":{"x":72.9553066166442,"y":474.4765663529185}},{"id":"Q80504","label":"Nicolae Ceaușescu","position":{"x":195,"y":570}}],"connections":{"Q5879":["Q517","Q484141","Q214622"],"Q214622":["Q1394","Q5879","Q187550","Q2658023","Q12875223"],"Q1394":["Q855","Q214622"],"Q855":["Q1394","Q80504"],"Q517":["Q5879"],"Q484141":["Q5879"],"Q12875223":["Q214622"],"Q187550":["Q214622"],"Q2658023":["Q214622"],"Q34060":[],"Q132899":[],"Q80504":["Q855"]},"optimalPath":["Q5879","Q214622","Q1394","Q855","Q80504"],"difficulty":"easy"},"pathLabels":["Johann Wolfgang von Goethe","Nikos Kazantzakis","Vladimir Lenin","Joseph Stalin","Nicolae Ceaușescu"],"qcScore":7,"qualityScore":62.5,"edgeLabels":{"Q855|Q1394":"connected to","Q1394|Q855":"connected to","Q5879|Q517":"connected to","Q517|Q5879":"connected to","Q80504|Q855":"connected to","Q855|Q80504":"connected to","Q484141|Q5879":"connected to","Q5879|Q484141":"connected to","Q214622|Q1394":"connected to","Q1394|Q214622":"connected to","Q214622|Q5879":"connected to","Q5879|Q214622":"connected to","Q214622|Q187550":"connected to","Q187550|Q214622":"connected to","Q214622|Q2658023":"connected to","Q2658023|Q214622":"connected to","Q214622|Q12875223":"connected to","Q12875223|Q214622":"connected to"}}