{"puzzle":{"startId":"Q2105","endId":"Q27645","bubbles":[{"id":"Q2105","label":"Jacques Chirac","position":{"x":195,"y":80}},{"id":"Q192821","label":"French Communist Party","position":{"x":77.04705867502669,"y":174.31829484938797}},{"id":"Q53783","label":"Enver Hoxha","position":{"x":187.16657212755422,"y":178.99531692145743}},{"id":"Q9061","label":"Karl Marx","position":{"x":320.69878369951834,"y":165.0999128314069}},{"id":"Q192348","label":"Benedetto Croce","position":{"x":79.63766622278202,"y":279.95662694252326}},{"id":"Q642562","label":"Communist League","position":{"x":194.55498276630155,"y":273.65802328971694}},{"id":"Q1052584","label":"Rally for the Republic","position":{"x":317.324059690592,"y":271.2407582676781}},{"id":"Q537850","label":"Communist Party of Belgium","position":{"x":76.74790743743186,"y":369.9351177232649}},{"id":"Q201221","label":"Alexander Herzen","position":{"x":201.61306915634427,"y":369.7641297379455}},{"id":"Q451791","label":"Giorgia Meloni","position":{"x":317.0205883822896,"y":379.80627321300875}},{"id":"Q160847","label":"Hideki Tojo","position":{"x":67.90398420256093,"y":474.351659855933}},{"id":"Q27645","label":"Mikhail Bakunin","position":{"x":195,"y":570}}],"connections":{"Q2105":["Q192821","Q1052584"],"Q192821":["Q2105","Q53783"],"Q53783":["Q192821","Q537850","Q9061"],"Q9061":["Q642562","Q27645","Q53783","Q192348"],"Q192348":["Q9061"],"Q642562":["Q9061"],"Q1052584":["Q2105"],"Q537850":["Q53783"],"Q201221":["Q27645"],"Q451791":[],"Q160847":[],"Q27645":["Q9061","Q201221"]},"optimalPath":["Q2105","Q192821","Q53783","Q9061","Q27645"],"difficulty":"medium"},"pathLabels":["Jacques Chirac","French Communist Party","Enver Hoxha","Karl Marx","Mikhail Bakunin"],"qcScore":8,"qualityScore":56.64066666666667,"narrative":"Dive into a world where Jacques Chirac's early flirtation with political ideology connects through the intricate web of the French Communist Party and leads you to Enver Hoxha. From there, the intellectual linchpins of Karl Marx and Mikhail Bakunin map out the ideological shifts that have shaped revolutionary thought — the ultimate testament to history's adaptive discourse.","edgeLabels":{"Q9061|Q642562":"member of","Q642562|Q9061":"member of","Q2105|Q192821":"member of","Q192821|Q2105":"member of","Q2105|Q1052584":"member of","Q1052584|Q2105":"member of","Q53783|Q192821":"member of","Q192821|Q53783":"member of","Q53783|Q537850":"member of","Q537850|Q53783":"member of","Q27645|Q9061":"connected to","Q9061|Q27645":"connected to","Q27645|Q201221":"connected to","Q201221|Q27645":"connected to","Q53783|Q9061":"connected to","Q9061|Q53783":"connected to","Q192348|Q9061":"connected to","Q9061|Q192348":"connected to"}}