{"puzzle":{"startId":"Q14060","endId":"Q124617","bubbles":[{"id":"Q14060","label":"Erwin Rommel","position":{"x":195,"y":80}},{"id":"Q41304","label":"Weimar Republic","position":{"x":82.55638429505059,"y":176.106999692406}},{"id":"Q57309","label":"Erich Mielke","position":{"x":193.6463385843646,"y":171.50171089683312}},{"id":"Q15180","label":"Soviet Union","position":{"x":320.29501257763746,"y":178.34736043729055}},{"id":"Q7318","label":"Nazi Germany","position":{"x":82.63926693086862,"y":260.2439213549845}},{"id":"Q43287","label":"German Empire","position":{"x":204.58857559063188,"y":266.28926434686116}},{"id":"Q57141","label":"Günther von Kluge","position":{"x":321.00321627150873,"y":265.0625773948099}},{"id":"Q57144","label":"Walter von Reichenau","position":{"x":76.65699982257895,"y":360.3921218308154}},{"id":"Q183","label":"Germany","position":{"x":199.35528315190422,"y":379.89070247982454}},{"id":"Q10957559","label":"Principality of Moldavia","position":{"x":310.8517790190499,"y":366.740061959546}},{"id":"Q1193377","label":"Muhammad Najib Al-Rubaiy","position":{"x":83.02500242464083,"y":476.7844638802687}},{"id":"Q124617","label":"Georgy Zhukov","position":{"x":195,"y":570}}],"connections":{"Q14060":["Q7318","Q41304","Q43287"],"Q41304":["Q14060","Q57141","Q57144","Q57309"],"Q57309":["Q183","Q15180","Q41304","Q43287"],"Q15180":["Q124617","Q57309"],"Q7318":["Q14060","Q57141"],"Q43287":["Q14060","Q57309"],"Q57141":["Q7318","Q41304"],"Q57144":["Q41304"],"Q183":["Q57309"],"Q10957559":[],"Q1193377":[],"Q124617":["Q15180"]},"optimalPath":["Q14060","Q41304","Q57309","Q15180","Q124617"],"difficulty":"easy"},"pathLabels":["Erwin Rommel","Weimar Republic","Erich Mielke","Soviet Union","Georgy Zhukov"],"qcScore":7,"qualityScore":52.5}