{"puzzle":{"startId":"Q270935","endId":"Q49575","bubbles":[{"id":"Q270935","label":"Chris Cornell","position":{"x":195,"y":80}},{"id":"Q4413456","label":"Republic Records","position":{"x":73.45521432911985,"y":176.88108977095342}},{"id":"Q15897","label":"Amy Winehouse","position":{"x":198.74778773466088,"y":165.4265766089796}},{"id":"Q104358","label":"Billie Holiday","position":{"x":305.059938228555,"y":164.18914899399334}},{"id":"Q193023","label":"Capitol Records","position":{"x":82.49174098249827,"y":261.11879561247576}},{"id":"Q778673","label":"Sub Pop","position":{"x":200.83220983915155,"y":271.0277135095048}},{"id":"Q639182","label":"SST Records","position":{"x":305.8736712921967,"y":267.72623990590785}},{"id":"Q277626","label":"A&M Records","position":{"x":83.97741462229683,"y":368.1654786368218}},{"id":"Q21621919","label":"Post Malone","position":{"x":204.07477243126453,"y":370.9516622173651}},{"id":"Q15869","label":"Freddie Mercury","position":{"x":305.79605447328055,"y":379.14942848505024}},{"id":"Q902640","label":"Losing Grip","position":{"x":65.78018895178052,"y":471.45904166903614}},{"id":"Q49575","label":"Dizzy Gillespie","position":{"x":195,"y":570}}],"connections":{"Q270935":["Q277626","Q639182","Q778673","Q4413456"],"Q4413456":["Q15897","Q21621919","Q270935"],"Q15897":["Q4413456","Q104358"],"Q104358":["Q193023","Q15897"],"Q193023":["Q104358","Q49575"],"Q778673":["Q270935"],"Q639182":["Q270935"],"Q277626":["Q270935"],"Q21621919":["Q4413456"],"Q15869":[],"Q902640":[],"Q49575":["Q193023"]},"optimalPath":["Q270935","Q4413456","Q15897","Q104358","Q193023","Q49575"],"difficulty":"hard"},"pathLabels":["Chris Cornell","Republic Records","Amy Winehouse","Billie Holiday","Capitol Records","Dizzy Gillespie"],"qcScore":8,"qualityScore":50.50626666666666,"narrative":"Dive into the rich tapestry of jazz and soul as you embark from the gritty, soulful depths charted by Chris Cornell at Republic Records to the timeless elegance of Amy Winehouse's renditions of jazz standards. From there, soar back in time to Billie Holiday, a voice adorned with sorrow and strength, linked by a shared connection to Capitol Records with Dizzy Gillespie, a pivotal figure in the bebop revolution, whose trumpet once breathed vibrancy into the corners of modern jazz.","edgeLabels":{"Q15897|Q4413456":"signed to","Q4413456|Q15897":"signed to","Q104358|Q193023":"signed to","Q193023|Q104358":"signed to","Q49575|Q193023":"signed to","Q193023|Q49575":"signed to","Q21621919|Q4413456":"signed to","Q4413456|Q21621919":"signed to","Q270935|Q277626":"signed to","Q277626|Q270935":"signed to","Q270935|Q639182":"signed to","Q639182|Q270935":"signed to","Q270935|Q778673":"signed to","Q778673|Q270935":"signed to","Q270935|Q4413456":"signed to","Q4413456|Q270935":"signed to","Q15897|Q104358":"influenced by","Q104358|Q15897":"influenced by"}}