{"puzzle":{"startId":"Q132537","endId":"Q57100","bubbles":[{"id":"Q132537","label":"Robert Oppenheimer","position":{"x":195,"y":80}},{"id":"Q168756","label":"University of California, Berkeley","position":{"x":66.11580265705288,"y":164.06576421187305}},{"id":"Q106399","label":"John Howard Northrop","position":{"x":192.42586707055932,"y":179.24085525155482}},{"id":"Q49088","label":"Columbia University","position":{"x":310.2097294844161,"y":171.27804075123703}},{"id":"Q127050","label":"Manhattan Project","position":{"x":79.21631193766018,"y":263.4924150357256}},{"id":"Q161562","label":"California Institute of Technology","position":{"x":203.4297691534844,"y":265.4986965769459}},{"id":"Q635642","label":"Institute for Advanced Study","position":{"x":320.54278473800053,"y":273.80183980076816}},{"id":"Q107420","label":"Sheldon Glashow","position":{"x":79.77395246970276,"y":379.8020695221923}},{"id":"Q334760","label":"Shing-Tung Yau","position":{"x":193.42254440893103,"y":369.2038676465343}},{"id":"Q28647524","label":"Reactive Scientific Research Institute","position":{"x":323.45271097671196,"y":367.64598362267793}},{"id":"Q97446386","label":"Fábrica Militar de Aviones","position":{"x":65.4839624079642,"y":464.2317660317746}},{"id":"Q57100","label":"Maria Goeppert Mayer","position":{"x":195,"y":570}}],"connections":{"Q132537":["Q127050","Q161562","Q168756","Q635642"],"Q168756":["Q132537","Q106399","Q107420","Q334760"],"Q106399":["Q49088","Q168756"],"Q49088":["Q57100","Q106399"],"Q127050":["Q132537"],"Q161562":["Q132537"],"Q635642":["Q132537"],"Q107420":["Q168756"],"Q334760":["Q168756"],"Q28647524":[],"Q97446386":[],"Q57100":["Q49088"]},"optimalPath":["Q132537","Q168756","Q106399","Q49088","Q57100"],"difficulty":"easy"},"pathLabels":["Robert Oppenheimer","University of California, Berkeley","John Howard Northrop","Columbia University","Maria Goeppert Mayer"],"qcScore":7,"qualityScore":56.333333333333336,"edgeLabels":{"Q132537|Q127050":"worked at","Q127050|Q132537":"worked at","Q132537|Q161562":"worked at","Q161562|Q132537":"worked at","Q132537|Q168756":"worked at","Q168756|Q132537":"worked at","Q132537|Q635642":"worked at","Q635642|Q132537":"worked at","Q57100|Q49088":"worked at","Q49088|Q57100":"worked at","Q106399|Q49088":"worked at","Q49088|Q106399":"worked at","Q106399|Q168756":"worked at","Q168756|Q106399":"worked at","Q107420|Q168756":"worked at","Q168756|Q107420":"worked at","Q334760|Q168756":"worked at","Q168756|Q334760":"worked at"}}